typedclasses/__init__.py
typedclasses/core.py
typedclasses-0.0.1.dist-info/LICENSE
typedclasses-0.0.1.dist-info/METADATA
typedclasses-0.0.1.dist-info/WHEEL
typedclasses-0.0.1.dist-info/top_level.txt
typedclasses-0.0.1.dist-info/RECORD
