Metadata-Version: 2.1
Name: typedclasses
Version: 0.0.1
Summary: Python classes with types validation at runtime.
Home-page: https://github.com/nerdguyahmad/typedclasses
Author: nerdguyahmad
License: MIT
Project-URL: Documentation, https://github.com/nerdguyahmad/typedclasses/wiki
Project-URL: Issue tracker, https://github.com/nerdguyahmad/typedclasses/issues
Platform: UNKNOWN
Classifier: Development Status :: 5 - Production/Stable
Classifier: License :: OSI Approved :: MIT License
Classifier: Intended Audience :: Developers
Classifier: Natural Language :: English
Classifier: Operating System :: OS Independent
Classifier: Programming Language :: Python :: 3.8
Classifier: Programming Language :: Python :: 3.9
Classifier: Topic :: Internet
Classifier: Topic :: Software Development :: Libraries
Classifier: Topic :: Software Development :: Libraries :: Python Modules
Classifier: Topic :: Utilities
Classifier: Typing :: Typed
Requires-Python: >=3.8.0
